__init__.py
comment_recommendation_framework/Dockerfile
comment_recommendation_framework/Pipfile
comment_recommendation_framework/Pipfile.lock
comment_recommendation_framework/__init__.py
comment_recommendation_framework/__main__.py
comment_recommendation_framework/docker-compose.api.yml
comment_recommendation_framework/docker-compose.csv.yml
comment_recommendation_framework/docker-compose.embed.yml
comment_recommendation_framework/docker-compose.scraping.yml
comment_recommendation_framework/docker-compose.test.yml
comment_recommendation_framework/wait-for-it.sh
comment_recommendation_framework/RecommendationSystem/__init__.py
comment_recommendation_framework/RecommendationSystem/API/__init__.py
comment_recommendation_framework/RecommendationSystem/API/manage.py
comment_recommendation_framework/RecommendationSystem/API/API/__init__.py
comment_recommendation_framework/RecommendationSystem/API/API/asgi.py
comment_recommendation_framework/RecommendationSystem/API/API/settings.py
comment_recommendation_framework/RecommendationSystem/API/API/urls.py
comment_recommendation_framework/RecommendationSystem/API/API/wsgi.py
comment_recommendation_framework/RecommendationSystem/API/RESTApi/__init__.py
comment_recommendation_framework/RecommendationSystem/API/RESTApi/abstract_model.py
comment_recommendation_framework/RecommendationSystem/API/RESTApi/apps.py
comment_recommendation_framework/RecommendationSystem/API/RESTApi/urls.py
comment_recommendation_framework/RecommendationSystem/API/RESTApi/views.py
comment_recommendation_framework/RecommendationSystem/DB/__init__.py
comment_recommendation_framework/RecommendationSystem/DB/utils.py
comment_recommendation_framework/RecommendationSystem/DB/db_models/__init__.py
comment_recommendation_framework/RecommendationSystem/DB/db_models/article.py
comment_recommendation_framework/RecommendationSystem/DB/db_models/comment.py
comment_recommendation_framework/RecommendationSystem/Embedder/__init__.py
comment_recommendation_framework-0.16.6.dist-info/LICENSE
comment_recommendation_framework-0.16.6.dist-info/METADATA
comment_recommendation_framework-0.16.6.dist-info/WHEEL
comment_recommendation_framework-0.16.6.dist-info/top_level.txt
comment_recommendation_framework-0.16.6.dist-info/RECORD
