Metadata-Version: 2.1
Name: comment-recommendation-framework
Version: 0.16.6
License-File: LICENSE
